LICENSE
README.md
setup.py
propagators/__init__.py
propagators/_cn_utils.c
propagators/_cn_utils.pyx
propagators/_utils.py
propagators/contfrac.c
propagators/contfrac.pyx
propagators/dispersion_relations.c
propagators/dispersion_relations.pyx
propagators/field.py
propagators/long_running_tests.py
propagators/math_utils.py
propagators/sspade.py
propagators/tests.py
propagators/ts.py
propagators/vis.py
propagators/wavenumber.py
pywaveprop.egg-info/PKG-INFO
pywaveprop.egg-info/SOURCES.txt
pywaveprop.egg-info/dependency_links.txt
pywaveprop.egg-info/not-zip-safe
pywaveprop.egg-info/requires.txt
pywaveprop.egg-info/top_level.txt
rwp/SSPade3d.py
rwp/__init__.py
rwp/antennas.py
rwp/crank_nicolson.py
rwp/environment.py
rwp/field.py
rwp/kediffraction.py
rwp/long_running_tests.py
rwp/petool.py
rwp/ssf.py
rwp/sspade.py
rwp/terrain.py
rwp/tests.py
rwp/tropospheric_attenuation.py
rwp/tworay.py
rwp/urban.py
rwp/vis.py
transforms/filon.py
transforms/frft.py
transforms/setup.py
transforms/tests.py
transforms/z_transform.py
transforms/fcc_fourier/__init__.py
transforms/fcc_fourier/fcc.py
transforms/fcc_fourier/tests.py
uwa/__init__.py
uwa/environment.py
uwa/field.py
uwa/ram.py
uwa/source.py
uwa/sspade.py
uwa/vis.py