Metadata-Version: 2.1
Name: pywaveprop
Version: 1.0.0
Summary: Wave propagation framework
Home-page: https://github.com/mikelytaev/wave-propagation
Author: Mikhail Lytaev
Author-email: mikelytaev@gmail.com
License: MIT
Keywords: wave propagation,parabolic equation,troposphere,underwater acoustics,diffraction,refraction
Platform: UNKNOWN
License-File: LICENSE
